guesser_game/GuesserGame.py
guesser_game/__init__.py
guesser_game/numberGuesserGame.py
some_guesser_game_package-0.0.1.dist-info/METADATA
some_guesser_game_package-0.0.1.dist-info/WHEEL
some_guesser_game_package-0.0.1.dist-info/top_level.txt
some_guesser_game_package-0.0.1.dist-info/RECORD
